youtube_pydantic_models/__init__.py
youtube_pydantic_models/base_model_config.py
youtube_pydantic_models/base_resource.py
youtube_pydantic_models/channel_resource.py
youtube_pydantic_models/errors.py
youtube_pydantic_models/list_response.py
youtube_pydantic_models/main.py
youtube_pydantic_models/parts.py
youtube_pydantic_models/playlist_resource.py
youtube_pydantic_models/quotas.py
youtube_pydantic_models/search_resource.py
youtube_pydantic_models/subparts.py
youtube_pydantic_models/video_resource.py
youtube_pydantic_models-0.2.2.dist-info/LICENSE
youtube_pydantic_models-0.2.2.dist-info/METADATA
youtube_pydantic_models-0.2.2.dist-info/WHEEL
youtube_pydantic_models-0.2.2.dist-info/top_level.txt
youtube_pydantic_models-0.2.2.dist-info/RECORD
