Metadata-Version: 2.1
Name: youtube-pydantic-models
Version: 0.2.2
Summary: Use Pydantic models to work with the YouTube API.
Author-email: Federico Gomez <gomez00federico@gmail.com>
License: MIT License
Project-URL: Homepage, https://github.com/fedeegmz/youtube-pydantic-models
Project-URL: Issues, https://github.com/fedeegmz/youtube-pydantic-models/issues
Project-URL: Documentation, https://fedeegmz.github.io/youtube-pydantic-models/
Keywords: youtube,youtube-api,youtubev3,youtube-v3,pydantic,pydantic-model
Classifier: Programming Language :: Python :: 3.7
Classifier: Programming Language :: Python :: 3.8
Classifier: Programming Language :: Python :: 3.9
Requires-Python: >=3.7
License-File: LICENSE
Requires-Dist: pydantic
Requires-Dist: requests
